package com.android.cglib.dx;

import com.android.cglib.dx.c.b.p;
import com.android.cglib.dx.c.b.r;
import com.android.cglib.dx.c.d.e;

public static final abstract enum BinaryOp {
  ADD, AND, DIVIDE, MULTIPLY, OR, REMAINDER, SHIFT_LEFT, SHIFT_RIGHT, SUBTRACT, UNSIGNED_SHIFT_RIGHT, XOR;
  
  static  {
    // Byte code:
    //   0: new com/android/cglib/dx/BinaryOp$1
    //   3: dup
    //   4: ldc 'ADD'
    //   6: iconst_0
    //   7: invokespecial <init> : (Ljava/lang/String;I)V
    //   10: putstatic com/android/cglib/dx/BinaryOp.ADD : Lcom/android/cglib/dx/BinaryOp;
    //   13: new com/android/cglib/dx/BinaryOp$2
    //   16: dup
    //   17: ldc 'SUBTRACT'
    //   19: iconst_1
    //   20: invokespecial <init> : (Ljava/lang/String;I)V
    //   23: putstatic com/android/cglib/dx/BinaryOp.SUBTRACT : Lcom/android/cglib/dx/BinaryOp;
    //   26: new com/android/cglib/dx/BinaryOp$3
    //   29: dup
    //   30: ldc 'MULTIPLY'
    //   32: iconst_2
    //   33: invokespecial <init> : (Ljava/lang/String;I)V
    //   36: putstatic com/android/cglib/dx/BinaryOp.MULTIPLY : Lcom/android/cglib/dx/BinaryOp;
    //   39: new com/android/cglib/dx/BinaryOp$4
    //   42: dup
    //   43: ldc 'DIVIDE'
    //   45: iconst_3
    //   46: invokespecial <init> : (Ljava/lang/String;I)V
    //   49: putstatic com/android/cglib/dx/BinaryOp.DIVIDE : Lcom/android/cglib/dx/BinaryOp;
    //   52: new com/android/cglib/dx/BinaryOp$5
    //   55: dup
    //   56: ldc 'REMAINDER'
    //   58: iconst_4
    //   59: invokespecial <init> : (Ljava/lang/String;I)V
    //   62: putstatic com/android/cglib/dx/BinaryOp.REMAINDER : Lcom/android/cglib/dx/BinaryOp;
    //   65: new com/android/cglib/dx/BinaryOp$6
    //   68: dup
    //   69: ldc 'AND'
    //   71: iconst_5
    //   72: invokespecial <init> : (Ljava/lang/String;I)V
    //   75: putstatic com/android/cglib/dx/BinaryOp.AND : Lcom/android/cglib/dx/BinaryOp;
    //   78: new com/android/cglib/dx/BinaryOp$7
    //   81: dup
    //   82: ldc 'OR'
    //   84: bipush #6
    //   86: invokespecial <init> : (Ljava/lang/String;I)V
    //   89: putstatic com/android/cglib/dx/BinaryOp.OR : Lcom/android/cglib/dx/BinaryOp;
    //   92: new com/android/cglib/dx/BinaryOp$8
    //   95: dup
    //   96: ldc 'XOR'
    //   98: bipush #7
    //   100: invokespecial <init> : (Ljava/lang/String;I)V
    //   103: putstatic com/android/cglib/dx/BinaryOp.XOR : Lcom/android/cglib/dx/BinaryOp;
    //   106: new com/android/cglib/dx/BinaryOp$9
    //   109: dup
    //   110: ldc 'SHIFT_LEFT'
    //   112: bipush #8
    //   114: invokespecial <init> : (Ljava/lang/String;I)V
    //   117: putstatic com/android/cglib/dx/BinaryOp.SHIFT_LEFT : Lcom/android/cglib/dx/BinaryOp;
    //   120: new com/android/cglib/dx/BinaryOp$10
    //   123: dup
    //   124: ldc 'SHIFT_RIGHT'
    //   126: bipush #9
    //   128: invokespecial <init> : (Ljava/lang/String;I)V
    //   131: putstatic com/android/cglib/dx/BinaryOp.SHIFT_RIGHT : Lcom/android/cglib/dx/BinaryOp;
    //   134: new com/android/cglib/dx/BinaryOp$11
    //   137: dup
    //   138: ldc 'UNSIGNED_SHIFT_RIGHT'
    //   140: bipush #10
    //   142: invokespecial <init> : (Ljava/lang/String;I)V
    //   145: putstatic com/android/cglib/dx/BinaryOp.UNSIGNED_SHIFT_RIGHT : Lcom/android/cglib/dx/BinaryOp;
    //   148: bipush #11
    //   150: anewarray com/android/cglib/dx/BinaryOp
    //   153: dup
    //   154: iconst_0
    //   155: getstatic com/android/cglib/dx/BinaryOp.ADD : Lcom/android/cglib/dx/BinaryOp;
    //   158: aastore
    //   159: dup
    //   160: iconst_1
    //   161: getstatic com/android/cglib/dx/BinaryOp.SUBTRACT : Lcom/android/cglib/dx/BinaryOp;
    //   164: aastore
    //   165: dup
    //   166: iconst_2
    //   167: getstatic com/android/cglib/dx/BinaryOp.MULTIPLY : Lcom/android/cglib/dx/BinaryOp;
    //   170: aastore
    //   171: dup
    //   172: iconst_3
    //   173: getstatic com/android/cglib/dx/BinaryOp.DIVIDE : Lcom/android/cglib/dx/BinaryOp;
    //   176: aastore
    //   177: dup
    //   178: iconst_4
    //   179: getstatic com/android/cglib/dx/BinaryOp.REMAINDER : Lcom/android/cglib/dx/BinaryOp;
    //   182: aastore
    //   183: dup
    //   184: iconst_5
    //   185: getstatic com/android/cglib/dx/BinaryOp.AND : Lcom/android/cglib/dx/BinaryOp;
    //   188: aastore
    //   189: dup
    //   190: bipush #6
    //   192: getstatic com/android/cglib/dx/BinaryOp.OR : Lcom/android/cglib/dx/BinaryOp;
    //   195: aastore
    //   196: dup
    //   197: bipush #7
    //   199: getstatic com/android/cglib/dx/BinaryOp.XOR : Lcom/android/cglib/dx/BinaryOp;
    //   202: aastore
    //   203: dup
    //   204: bipush #8
    //   206: getstatic com/android/cglib/dx/BinaryOp.SHIFT_LEFT : Lcom/android/cglib/dx/BinaryOp;
    //   209: aastore
    //   210: dup
    //   211: bipush #9
    //   213: getstatic com/android/cglib/dx/BinaryOp.SHIFT_RIGHT : Lcom/android/cglib/dx/BinaryOp;
    //   216: aastore
    //   217: dup
    //   218: bipush #10
    //   220: getstatic com/android/cglib/dx/BinaryOp.UNSIGNED_SHIFT_RIGHT : Lcom/android/cglib/dx/BinaryOp;
    //   223: aastore
    //   224: putstatic com/android/cglib/dx/BinaryOp.$VALUES : [Lcom/android/cglib/dx/BinaryOp;
    //   227: return
  }
  
  abstract p rop(e parame);
}


/* Location:              D:\apk反编译\classes-dex2jar.jar!\com\android\cglib\dx\BinaryOp.class
 * Java compiler version: 6 (50.0)
 * JD-Core Version:       1.0.7
 */