package com.android.cglib.dx;

import com.android.cglib.dx.c.b.p;
import com.android.cglib.dx.c.b.r;
import com.android.cglib.dx.c.d.e;

public static final abstract enum Comparison {
  EQ, GE, GT, LE, LT, NE;
  
  static  {
    // Byte code:
    //   0: new com/android/cglib/dx/Comparison$1
    //   3: dup
    //   4: ldc 'LT'
    //   6: iconst_0
    //   7: invokespecial <init> : (Ljava/lang/String;I)V
    //   10: putstatic com/android/cglib/dx/Comparison.LT : Lcom/android/cglib/dx/Comparison;
    //   13: new com/android/cglib/dx/Comparison$2
    //   16: dup
    //   17: ldc 'LE'
    //   19: iconst_1
    //   20: invokespecial <init> : (Ljava/lang/String;I)V
    //   23: putstatic com/android/cglib/dx/Comparison.LE : Lcom/android/cglib/dx/Comparison;
    //   26: new com/android/cglib/dx/Comparison$3
    //   29: dup
    //   30: ldc 'EQ'
    //   32: iconst_2
    //   33: invokespecial <init> : (Ljava/lang/String;I)V
    //   36: putstatic com/android/cglib/dx/Comparison.EQ : Lcom/android/cglib/dx/Comparison;
    //   39: new com/android/cglib/dx/Comparison$4
    //   42: dup
    //   43: ldc 'GE'
    //   45: iconst_3
    //   46: invokespecial <init> : (Ljava/lang/String;I)V
    //   49: putstatic com/android/cglib/dx/Comparison.GE : Lcom/android/cglib/dx/Comparison;
    //   52: new com/android/cglib/dx/Comparison$5
    //   55: dup
    //   56: ldc 'GT'
    //   58: iconst_4
    //   59: invokespecial <init> : (Ljava/lang/String;I)V
    //   62: putstatic com/android/cglib/dx/Comparison.GT : Lcom/android/cglib/dx/Comparison;
    //   65: new com/android/cglib/dx/Comparison$6
    //   68: dup
    //   69: ldc 'NE'
    //   71: iconst_5
    //   72: invokespecial <init> : (Ljava/lang/String;I)V
    //   75: putstatic com/android/cglib/dx/Comparison.NE : Lcom/android/cglib/dx/Comparison;
    //   78: bipush #6
    //   80: anewarray com/android/cglib/dx/Comparison
    //   83: dup
    //   84: iconst_0
    //   85: getstatic com/android/cglib/dx/Comparison.LT : Lcom/android/cglib/dx/Comparison;
    //   88: aastore
    //   89: dup
    //   90: iconst_1
    //   91: getstatic com/android/cglib/dx/Comparison.LE : Lcom/android/cglib/dx/Comparison;
    //   94: aastore
    //   95: dup
    //   96: iconst_2
    //   97: getstatic com/android/cglib/dx/Comparison.EQ : Lcom/android/cglib/dx/Comparison;
    //   100: aastore
    //   101: dup
    //   102: iconst_3
    //   103: getstatic com/android/cglib/dx/Comparison.GE : Lcom/android/cglib/dx/Comparison;
    //   106: aastore
    //   107: dup
    //   108: iconst_4
    //   109: getstatic com/android/cglib/dx/Comparison.GT : Lcom/android/cglib/dx/Comparison;
    //   112: aastore
    //   113: dup
    //   114: iconst_5
    //   115: getstatic com/android/cglib/dx/Comparison.NE : Lcom/android/cglib/dx/Comparison;
    //   118: aastore
    //   119: putstatic com/android/cglib/dx/Comparison.$VALUES : [Lcom/android/cglib/dx/Comparison;
    //   122: return
  }
  
  abstract p rop(e parame);
}


/* Location:              D:\apk反编译\classes-dex2jar.jar!\com\android\cglib\dx\Comparison.class
 * Java compiler version: 6 (50.0)
 * JD-Core Version:       1.0.7
 */