package com.android.cglib.dx.b.a;

public static final abstract enum a {
  A, B, C, D, E, F, G, H, I, J, K, L, M, N, a, b, c, d, e, f, g, h, i, j, k, l, m, n, o, p, q, r, s, t, u, v, w, x, y, z;
  
  static  {
    // Byte code:
    //   0: new com/android/cglib/dx/b/a/a$1
    //   3: dup
    //   4: ldc 'FORMAT_00X'
    //   6: iconst_0
    //   7: invokespecial <init> : (Ljava/lang/String;I)V
    //   10: putstatic com/android/cglib/dx/b/a/a.a : Lcom/android/cglib/dx/b/a/a;
    //   13: new com/android/cglib/dx/b/a/a$12
    //   16: dup
    //   17: ldc 'FORMAT_10X'
    //   19: iconst_1
    //   20: invokespecial <init> : (Ljava/lang/String;I)V
    //   23: putstatic com/android/cglib/dx/b/a/a.b : Lcom/android/cglib/dx/b/a/a;
    //   26: new com/android/cglib/dx/b/a/a$23
    //   29: dup
    //   30: ldc 'FORMAT_12X'
    //   32: iconst_2
    //   33: invokespecial <init> : (Ljava/lang/String;I)V
    //   36: putstatic com/android/cglib/dx/b/a/a.c : Lcom/android/cglib/dx/b/a/a;
    //   39: new com/android/cglib/dx/b/a/a$34
    //   42: dup
    //   43: ldc 'FORMAT_11N'
    //   45: iconst_3
    //   46: invokespecial <init> : (Ljava/lang/String;I)V
    //   49: putstatic com/android/cglib/dx/b/a/a.d : Lcom/android/cglib/dx/b/a/a;
    //   52: new com/android/cglib/dx/b/a/a$36
    //   55: dup
    //   56: ldc 'FORMAT_11X'
    //   58: iconst_4
    //   59: invokespecial <init> : (Ljava/lang/String;I)V
    //   62: putstatic com/android/cglib/dx/b/a/a.e : Lcom/android/cglib/dx/b/a/a;
    //   65: new com/android/cglib/dx/b/a/a$37
    //   68: dup
    //   69: ldc 'FORMAT_10T'
    //   71: iconst_5
    //   72: invokespecial <init> : (Ljava/lang/String;I)V
    //   75: putstatic com/android/cglib/dx/b/a/a.f : Lcom/android/cglib/dx/b/a/a;
    //   78: new com/android/cglib/dx/b/a/a$38
    //   81: dup
    //   82: ldc 'FORMAT_20T'
    //   84: bipush #6
    //   86: invokespecial <init> : (Ljava/lang/String;I)V
    //   89: putstatic com/android/cglib/dx/b/a/a.g : Lcom/android/cglib/dx/b/a/a;
    //   92: new com/android/cglib/dx/b/a/a$39
    //   95: dup
    //   96: ldc 'FORMAT_20BC'
    //   98: bipush #7
    //   100: invokespecial <init> : (Ljava/lang/String;I)V
    //   103: putstatic com/android/cglib/dx/b/a/a.h : Lcom/android/cglib/dx/b/a/a;
    //   106: new com/android/cglib/dx/b/a/a$40
    //   109: dup
    //   110: ldc 'FORMAT_22X'
    //   112: bipush #8
    //   114: invokespecial <init> : (Ljava/lang/String;I)V
    //   117: putstatic com/android/cglib/dx/b/a/a.i : Lcom/android/cglib/dx/b/a/a;
    //   120: new com/android/cglib/dx/b/a/a$2
    //   123: dup
    //   124: ldc 'FORMAT_21T'
    //   126: bipush #9
    //   128: invokespecial <init> : (Ljava/lang/String;I)V
    //   131: putstatic com/android/cglib/dx/b/a/a.j : Lcom/android/cglib/dx/b/a/a;
    //   134: new com/android/cglib/dx/b/a/a$3
    //   137: dup
    //   138: ldc 'FORMAT_21S'
    //   140: bipush #10
    //   142: invokespecial <init> : (Ljava/lang/String;I)V
    //   145: putstatic com/android/cglib/dx/b/a/a.k : Lcom/android/cglib/dx/b/a/a;
    //   148: new com/android/cglib/dx/b/a/a$4
    //   151: dup
    //   152: ldc 'FORMAT_21H'
    //   154: bipush #11
    //   156: invokespecial <init> : (Ljava/lang/String;I)V
    //   159: putstatic com/android/cglib/dx/b/a/a.l : Lcom/android/cglib/dx/b/a/a;
    //   162: new com/android/cglib/dx/b/a/a$5
    //   165: dup
    //   166: ldc 'FORMAT_21C'
    //   168: bipush #12
    //   170: invokespecial <init> : (Ljava/lang/String;I)V
    //   173: putstatic com/android/cglib/dx/b/a/a.m : Lcom/android/cglib/dx/b/a/a;
    //   176: new com/android/cglib/dx/b/a/a$6
    //   179: dup
    //   180: ldc 'FORMAT_23X'
    //   182: bipush #13
    //   184: invokespecial <init> : (Ljava/lang/String;I)V
    //   187: putstatic com/android/cglib/dx/b/a/a.n : Lcom/android/cglib/dx/b/a/a;
    //   190: new com/android/cglib/dx/b/a/a$7
    //   193: dup
    //   194: ldc 'FORMAT_22B'
    //   196: bipush #14
    //   198: invokespecial <init> : (Ljava/lang/String;I)V
    //   201: putstatic com/android/cglib/dx/b/a/a.o : Lcom/android/cglib/dx/b/a/a;
    //   204: new com/android/cglib/dx/b/a/a$8
    //   207: dup
    //   208: ldc 'FORMAT_22T'
    //   210: bipush #15
    //   212: invokespecial <init> : (Ljava/lang/String;I)V
    //   215: putstatic com/android/cglib/dx/b/a/a.p : Lcom/android/cglib/dx/b/a/a;
    //   218: new com/android/cglib/dx/b/a/a$9
    //   221: dup
    //   222: ldc 'FORMAT_22S'
    //   224: bipush #16
    //   226: invokespecial <init> : (Ljava/lang/String;I)V
    //   229: putstatic com/android/cglib/dx/b/a/a.q : Lcom/android/cglib/dx/b/a/a;
    //   232: new com/android/cglib/dx/b/a/a$10
    //   235: dup
    //   236: ldc 'FORMAT_22C'
    //   238: bipush #17
    //   240: invokespecial <init> : (Ljava/lang/String;I)V
    //   243: putstatic com/android/cglib/dx/b/a/a.r : Lcom/android/cglib/dx/b/a/a;
    //   246: new com/android/cglib/dx/b/a/a$11
    //   249: dup
    //   250: ldc 'FORMAT_22CS'
    //   252: bipush #18
    //   254: invokespecial <init> : (Ljava/lang/String;I)V
    //   257: putstatic com/android/cglib/dx/b/a/a.s : Lcom/android/cglib/dx/b/a/a;
    //   260: new com/android/cglib/dx/b/a/a$13
    //   263: dup
    //   264: ldc 'FORMAT_30T'
    //   266: bipush #19
    //   268: invokespecial <init> : (Ljava/lang/String;I)V
    //   271: putstatic com/android/cglib/dx/b/a/a.t : Lcom/android/cglib/dx/b/a/a;
    //   274: new com/android/cglib/dx/b/a/a$14
    //   277: dup
    //   278: ldc 'FORMAT_32X'
    //   280: bipush #20
    //   282: invokespecial <init> : (Ljava/lang/String;I)V
    //   285: putstatic com/android/cglib/dx/b/a/a.u : Lcom/android/cglib/dx/b/a/a;
    //   288: new com/android/cglib/dx/b/a/a$15
    //   291: dup
    //   292: ldc 'FORMAT_31I'
    //   294: bipush #21
    //   296: invokespecial <init> : (Ljava/lang/String;I)V
    //   299: putstatic com/android/cglib/dx/b/a/a.v : Lcom/android/cglib/dx/b/a/a;
    //   302: new com/android/cglib/dx/b/a/a$16
    //   305: dup
    //   306: ldc 'FORMAT_31T'
    //   308: bipush #22
    //   310: invokespecial <init> : (Ljava/lang/String;I)V
    //   313: putstatic com/android/cglib/dx/b/a/a.w : Lcom/android/cglib/dx/b/a/a;
    //   316: new com/android/cglib/dx/b/a/a$17
    //   319: dup
    //   320: ldc 'FORMAT_31C'
    //   322: bipush #23
    //   324: invokespecial <init> : (Ljava/lang/String;I)V
    //   327: putstatic com/android/cglib/dx/b/a/a.x : Lcom/android/cglib/dx/b/a/a;
    //   330: new com/android/cglib/dx/b/a/a$18
    //   333: dup
    //   334: ldc 'FORMAT_35C'
    //   336: bipush #24
    //   338: invokespecial <init> : (Ljava/lang/String;I)V
    //   341: putstatic com/android/cglib/dx/b/a/a.y : Lcom/android/cglib/dx/b/a/a;
    //   344: new com/android/cglib/dx/b/a/a$19
    //   347: dup
    //   348: ldc_w 'FORMAT_35MS'
    //   351: bipush #25
    //   353: invokespecial <init> : (Ljava/lang/String;I)V
    //   356: putstatic com/android/cglib/dx/b/a/a.z : Lcom/android/cglib/dx/b/a/a;
    //   359: new com/android/cglib/dx/b/a/a$20
    //   362: dup
    //   363: ldc_w 'FORMAT_35MI'
    //   366: bipush #26
    //   368: invokespecial <init> : (Ljava/lang/String;I)V
    //   371: putstatic com/android/cglib/dx/b/a/a.A : Lcom/android/cglib/dx/b/a/a;
    //   374: new com/android/cglib/dx/b/a/a$21
    //   377: dup
    //   378: ldc_w 'FORMAT_3RC'
    //   381: bipush #27
    //   383: invokespecial <init> : (Ljava/lang/String;I)V
    //   386: putstatic com/android/cglib/dx/b/a/a.B : Lcom/android/cglib/dx/b/a/a;
    //   389: new com/android/cglib/dx/b/a/a$22
    //   392: dup
    //   393: ldc_w 'FORMAT_3RMS'
    //   396: bipush #28
    //   398: invokespecial <init> : (Ljava/lang/String;I)V
    //   401: putstatic com/android/cglib/dx/b/a/a.C : Lcom/android/cglib/dx/b/a/a;
    //   404: new com/android/cglib/dx/b/a/a$24
    //   407: dup
    //   408: ldc_w 'FORMAT_3RMI'
    //   411: bipush #29
    //   413: invokespecial <init> : (Ljava/lang/String;I)V
    //   416: putstatic com/android/cglib/dx/b/a/a.D : Lcom/android/cglib/dx/b/a/a;
    //   419: new com/android/cglib/dx/b/a/a$25
    //   422: dup
    //   423: ldc_w 'FORMAT_51L'
    //   426: bipush #30
    //   428: invokespecial <init> : (Ljava/lang/String;I)V
    //   431: putstatic com/android/cglib/dx/b/a/a.E : Lcom/android/cglib/dx/b/a/a;
    //   434: new com/android/cglib/dx/b/a/a$26
    //   437: dup
    //   438: ldc_w 'FORMAT_33X'
    //   441: bipush #31
    //   443: invokespecial <init> : (Ljava/lang/String;I)V
    //   446: putstatic com/android/cglib/dx/b/a/a.F : Lcom/android/cglib/dx/b/a/a;
    //   449: new com/android/cglib/dx/b/a/a$27
    //   452: dup
    //   453: ldc_w 'FORMAT_32S'
    //   456: bipush #32
    //   458: invokespecial <init> : (Ljava/lang/String;I)V
    //   461: putstatic com/android/cglib/dx/b/a/a.G : Lcom/android/cglib/dx/b/a/a;
    //   464: new com/android/cglib/dx/b/a/a$28
    //   467: dup
    //   468: ldc_w 'FORMAT_40SC'
    //   471: bipush #33
    //   473: invokespecial <init> : (Ljava/lang/String;I)V
    //   476: putstatic com/android/cglib/dx/b/a/a.H : Lcom/android/cglib/dx/b/a/a;
    //   479: new com/android/cglib/dx/b/a/a$29
    //   482: dup
    //   483: ldc_w 'FORMAT_41C'
    //   486: bipush #34
    //   488: invokespecial <init> : (Ljava/lang/String;I)V
    //   491: putstatic com/android/cglib/dx/b/a/a.I : Lcom/android/cglib/dx/b/a/a;
    //   494: new com/android/cglib/dx/b/a/a$30
    //   497: dup
    //   498: ldc_w 'FORMAT_52C'
    //   501: bipush #35
    //   503: invokespecial <init> : (Ljava/lang/String;I)V
    //   506: putstatic com/android/cglib/dx/b/a/a.J : Lcom/android/cglib/dx/b/a/a;
    //   509: new com/android/cglib/dx/b/a/a$31
    //   512: dup
    //   513: ldc_w 'FORMAT_5RC'
    //   516: bipush #36
    //   518: invokespecial <init> : (Ljava/lang/String;I)V
    //   521: putstatic com/android/cglib/dx/b/a/a.K : Lcom/android/cglib/dx/b/a/a;
    //   524: new com/android/cglib/dx/b/a/a$32
    //   527: dup
    //   528: ldc_w 'FORMAT_PACKED_SWITCH_PAYLOAD'
    //   531: bipush #37
    //   533: invokespecial <init> : (Ljava/lang/String;I)V
    //   536: putstatic com/android/cglib/dx/b/a/a.L : Lcom/android/cglib/dx/b/a/a;
    //   539: new com/android/cglib/dx/b/a/a$33
    //   542: dup
    //   543: ldc_w 'FORMAT_SPARSE_SWITCH_PAYLOAD'
    //   546: bipush #38
    //   548: invokespecial <init> : (Ljava/lang/String;I)V
    //   551: putstatic com/android/cglib/dx/b/a/a.M : Lcom/android/cglib/dx/b/a/a;
    //   554: new com/android/cglib/dx/b/a/a$35
    //   557: dup
    //   558: ldc_w 'FORMAT_FILL_ARRAY_DATA_PAYLOAD'
    //   561: bipush #39
    //   563: invokespecial <init> : (Ljava/lang/String;I)V
    //   566: putstatic com/android/cglib/dx/b/a/a.N : Lcom/android/cglib/dx/b/a/a;
    //   569: bipush #40
    //   571: anewarray com/android/cglib/dx/b/a/a
    //   574: dup
    //   575: iconst_0
    //   576: getstatic com/android/cglib/dx/b/a/a.a : Lcom/android/cglib/dx/b/a/a;
    //   579: aastore
    //   580: dup
    //   581: iconst_1
    //   582: getstatic com/android/cglib/dx/b/a/a.b : Lcom/android/cglib/dx/b/a/a;
    //   585: aastore
    //   586: dup
    //   587: iconst_2
    //   588: getstatic com/android/cglib/dx/b/a/a.c : Lcom/android/cglib/dx/b/a/a;
    //   591: aastore
    //   592: dup
    //   593: iconst_3
    //   594: getstatic com/android/cglib/dx/b/a/a.d : Lcom/android/cglib/dx/b/a/a;
    //   597: aastore
    //   598: dup
    //   599: iconst_4
    //   600: getstatic com/android/cglib/dx/b/a/a.e : Lcom/android/cglib/dx/b/a/a;
    //   603: aastore
    //   604: dup
    //   605: iconst_5
    //   606: getstatic com/android/cglib/dx/b/a/a.f : Lcom/android/cglib/dx/b/a/a;
    //   609: aastore
    //   610: dup
    //   611: bipush #6
    //   613: getstatic com/android/cglib/dx/b/a/a.g : Lcom/android/cglib/dx/b/a/a;
    //   616: aastore
    //   617: dup
    //   618: bipush #7
    //   620: getstatic com/android/cglib/dx/b/a/a.h : Lcom/android/cglib/dx/b/a/a;
    //   623: aastore
    //   624: dup
    //   625: bipush #8
    //   627: getstatic com/android/cglib/dx/b/a/a.i : Lcom/android/cglib/dx/b/a/a;
    //   630: aastore
    //   631: dup
    //   632: bipush #9
    //   634: getstatic com/android/cglib/dx/b/a/a.j : Lcom/android/cglib/dx/b/a/a;
    //   637: aastore
    //   638: dup
    //   639: bipush #10
    //   641: getstatic com/android/cglib/dx/b/a/a.k : Lcom/android/cglib/dx/b/a/a;
    //   644: aastore
    //   645: dup
    //   646: bipush #11
    //   648: getstatic com/android/cglib/dx/b/a/a.l : Lcom/android/cglib/dx/b/a/a;
    //   651: aastore
    //   652: dup
    //   653: bipush #12
    //   655: getstatic com/android/cglib/dx/b/a/a.m : Lcom/android/cglib/dx/b/a/a;
    //   658: aastore
    //   659: dup
    //   660: bipush #13
    //   662: getstatic com/android/cglib/dx/b/a/a.n : Lcom/android/cglib/dx/b/a/a;
    //   665: aastore
    //   666: dup
    //   667: bipush #14
    //   669: getstatic com/android/cglib/dx/b/a/a.o : Lcom/android/cglib/dx/b/a/a;
    //   672: aastore
    //   673: dup
    //   674: bipush #15
    //   676: getstatic com/android/cglib/dx/b/a/a.p : Lcom/android/cglib/dx/b/a/a;
    //   679: aastore
    //   680: dup
    //   681: bipush #16
    //   683: getstatic com/android/cglib/dx/b/a/a.q : Lcom/android/cglib/dx/b/a/a;
    //   686: aastore
    //   687: dup
    //   688: bipush #17
    //   690: getstatic com/android/cglib/dx/b/a/a.r : Lcom/android/cglib/dx/b/a/a;
    //   693: aastore
    //   694: dup
    //   695: bipush #18
    //   697: getstatic com/android/cglib/dx/b/a/a.s : Lcom/android/cglib/dx/b/a/a;
    //   700: aastore
    //   701: dup
    //   702: bipush #19
    //   704: getstatic com/android/cglib/dx/b/a/a.t : Lcom/android/cglib/dx/b/a/a;
    //   707: aastore
    //   708: dup
    //   709: bipush #20
    //   711: getstatic com/android/cglib/dx/b/a/a.u : Lcom/android/cglib/dx/b/a/a;
    //   714: aastore
    //   715: dup
    //   716: bipush #21
    //   718: getstatic com/android/cglib/dx/b/a/a.v : Lcom/android/cglib/dx/b/a/a;
    //   721: aastore
    //   722: dup
    //   723: bipush #22
    //   725: getstatic com/android/cglib/dx/b/a/a.w : Lcom/android/cglib/dx/b/a/a;
    //   728: aastore
    //   729: dup
    //   730: bipush #23
    //   732: getstatic com/android/cglib/dx/b/a/a.x : Lcom/android/cglib/dx/b/a/a;
    //   735: aastore
    //   736: dup
    //   737: bipush #24
    //   739: getstatic com/android/cglib/dx/b/a/a.y : Lcom/android/cglib/dx/b/a/a;
    //   742: aastore
    //   743: dup
    //   744: bipush #25
    //   746: getstatic com/android/cglib/dx/b/a/a.z : Lcom/android/cglib/dx/b/a/a;
    //   749: aastore
    //   750: dup
    //   751: bipush #26
    //   753: getstatic com/android/cglib/dx/b/a/a.A : Lcom/android/cglib/dx/b/a/a;
    //   756: aastore
    //   757: dup
    //   758: bipush #27
    //   760: getstatic com/android/cglib/dx/b/a/a.B : Lcom/android/cglib/dx/b/a/a;
    //   763: aastore
    //   764: dup
    //   765: bipush #28
    //   767: getstatic com/android/cglib/dx/b/a/a.C : Lcom/android/cglib/dx/b/a/a;
    //   770: aastore
    //   771: dup
    //   772: bipush #29
    //   774: getstatic com/android/cglib/dx/b/a/a.D : Lcom/android/cglib/dx/b/a/a;
    //   777: aastore
    //   778: dup
    //   779: bipush #30
    //   781: getstatic com/android/cglib/dx/b/a/a.E : Lcom/android/cglib/dx/b/a/a;
    //   784: aastore
    //   785: dup
    //   786: bipush #31
    //   788: getstatic com/android/cglib/dx/b/a/a.F : Lcom/android/cglib/dx/b/a/a;
    //   791: aastore
    //   792: dup
    //   793: bipush #32
    //   795: getstatic com/android/cglib/dx/b/a/a.G : Lcom/android/cglib/dx/b/a/a;
    //   798: aastore
    //   799: dup
    //   800: bipush #33
    //   802: getstatic com/android/cglib/dx/b/a/a.H : Lcom/android/cglib/dx/b/a/a;
    //   805: aastore
    //   806: dup
    //   807: bipush #34
    //   809: getstatic com/android/cglib/dx/b/a/a.I : Lcom/android/cglib/dx/b/a/a;
    //   812: aastore
    //   813: dup
    //   814: bipush #35
    //   816: getstatic com/android/cglib/dx/b/a/a.J : Lcom/android/cglib/dx/b/a/a;
    //   819: aastore
    //   820: dup
    //   821: bipush #36
    //   823: getstatic com/android/cglib/dx/b/a/a.K : Lcom/android/cglib/dx/b/a/a;
    //   826: aastore
    //   827: dup
    //   828: bipush #37
    //   830: getstatic com/android/cglib/dx/b/a/a.L : Lcom/android/cglib/dx/b/a/a;
    //   833: aastore
    //   834: dup
    //   835: bipush #38
    //   837: getstatic com/android/cglib/dx/b/a/a.M : Lcom/android/cglib/dx/b/a/a;
    //   840: aastore
    //   841: dup
    //   842: bipush #39
    //   844: getstatic com/android/cglib/dx/b/a/a.N : Lcom/android/cglib/dx/b/a/a;
    //   847: aastore
    //   848: putstatic com/android/cglib/dx/b/a/a.O : [Lcom/android/cglib/dx/b/a/a;
    //   851: return
  }
}


/* Location:              D:\apk反编译\classes-dex2jar.jar!\com\android\cglib\dx\b\a\a.class
 * Java compiler version: 6 (50.0)
 * JD-Core Version:       1.0.7
 */